GotGithub/README.md
GotGithub/__init__.py
GotGithub/__main__.py
GotGithub/file.epub
GotGithub/index.html
GotGithub/css/__init__.py
GotGithub/css/annotations.css
GotGithub/css/main.css
GotGithub/css/normalize.css
GotGithub/css/popup.css
GotGithub/font/__init__.py
GotGithub/font/fontello.eot
GotGithub/font/fontello.svg
GotGithub/font/fontello.ttf
GotGithub/font/fontello.woff
GotGithub/img/__init__.py
GotGithub/img/annotator-glyph-sprite.png
GotGithub/img/annotator-icon-sprite.png
GotGithub/img/apple-touch-icon.png
GotGithub/img/cancelfullscreen.png
GotGithub/img/close.png
GotGithub/img/fullscreen.png
GotGithub/img/loader.gif
GotGithub/img/menu-icon.png
GotGithub/img/save.png
GotGithub/img/saved.png
GotGithub/img/settings-s.png
GotGithub/img/settings.png
GotGithub/img/star.png
GotGithub/js/__init__.py
GotGithub/js/epub.js
GotGithub/js/epub.min.js
GotGithub/js/epub.min.map
GotGithub/js/hooks.min.js
GotGithub/js/hooks.min.map
GotGithub/js/reader.js
GotGithub/js/reader.js.map
GotGithub/js/reader.min.js
GotGithub/js/reader.min.map
GotGithub/js/hooks/__init__.py
GotGithub/js/hooks/extensions/__init__.py
GotGithub/js/hooks/extensions/highlight.js
GotGithub/js/libs/__init__.py
GotGithub/js/libs/jquery.min.js
GotGithub/js/libs/localforage.min.js
GotGithub/js/libs/screenfull.js
GotGithub/js/libs/screenfull.min.js
GotGithub/js/libs/zip.min.js
GotGithub/js/plugins/__init__.py
GotGithub/js/plugins/hypothesis.js
GotGithub/js/plugins/search.js
got_github-2024.3.1.0.dist-info/METADATA
got_github-2024.3.1.0.dist-info/WHEEL
got_github-2024.3.1.0.dist-info/entry_points.txt
got_github-2024.3.1.0.dist-info/top_level.txt
got_github-2024.3.1.0.dist-info/RECORD
